yta_transcriber/__init__.py
yta_transcriber/real_time.py
yta_transcriber/translator.py
yta_transcriber/web/__init__.py
yta_transcriber/web/root/index.html
yta_transcriber-0.0.3.dist-info/licenses/LICENSE
yta_transcriber-0.0.3.dist-info/METADATA
yta_transcriber-0.0.3.dist-info/WHEEL
yta_transcriber-0.0.3.dist-info/RECORD
